Metadata-Version: 1.0
Name: nlp-zero
Version: 0.1.6
Summary: 无监督NLP工具包|unsupervised nlp toolkit
Home-page: https://kexue.fm
Author: bojone
Author-email: bojone@spaces.ac.cn
License: MIT Licence
Keywords: nlp tokenizer unsupervised parser 互信息 新词发现
Platform: any
